monapy/__init__.py
monapy/binding.py
monapy/step/__init__.py
monapy/step/core.py
monapy-0.6.0.dist-info/LICENSE
monapy-0.6.0.dist-info/METADATA
monapy-0.6.0.dist-info/WHEEL
monapy-0.6.0.dist-info/top_level.txt
monapy-0.6.0.dist-info/RECORD
