Metadata-Version: 2.1
Name: monapy
Version: 0.6.0
Summary: Python Library for declarative programming.
Home-page: https://github.com/andriystr/Monapy
Author: Andriy Stremeluk
Author-email: astremeluk@gmail.com
License: MIT
Classifier: Programming Language :: Python :: 3.6
Classifier: License :: OSI Approved :: MIT License
Classifier: Operating System :: OS Independent
Requires-Python: >=3.6
License-File: LICENSE
